README.md
setup.cfg
setup.py
openapi_client/__init__.py
openapi_client/api_client.py
openapi_client/configuration.py
openapi_client/exceptions.py
openapi_client/model_utils.py
openapi_client/rest.py
openapi_client/api/__init__.py
openapi_client/api/account_creation_api.py
openapi_client/api/cyberscan_api.py
openapi_client/api/member_deactivation_api.py
openapi_client/api/member_information_api.py
openapi_client/api/product_activation_api.py
openapi_client/apis/__init__.py
openapi_client/model/__init__.py
openapi_client/model/activate_post_dto.py
openapi_client/model/cancel_subscription_response.py
openapi_client/model/create_user_dto.py
openapi_client/model/create_user_response_dto.py
openapi_client/model/cyber_scan_exposures_get_dto.py
openapi_client/model/cyber_scan_exposures_get_dto_items_inner.py
openapi_client/model/cyber_scan_exposures_get_dto_items_inner_source_details.py
openapi_client/model/cyber_scan_item_dto.py
openapi_client/model/cyberscan_get_dto.py
openapi_client/model/cyberscan_hash_put_dto.py
openapi_client/model/cyberscan_post_dto.py
openapi_client/model/cyberscan_response_dto.py
openapi_client/model/cyberscan_summary_get_dto.py
openapi_client/model/cyberscan_summary_get_dto_bank_account_inner.py
openapi_client/model/member_cancel_put_dto.py
openapi_client/model/member_subscription_get_dto.py
openapi_client/model/member_subscription_get_dto_service_status.py
openapi_client/model/order_get_dto.py
openapi_client/model/order_get_dto_payment_details.py
openapi_client/model/order_get_dto_payment_details_price.py
openapi_client/model/order_get_dto_purchase_details.py
openapi_client/model/order_post_dto.py
openapi_client/models/__init__.py
rd_idx_client.egg-info/PKG-INFO
rd_idx_client.egg-info/SOURCES.txt
rd_idx_client.egg-info/dependency_links.txt
rd_idx_client.egg-info/requires.txt
rd_idx_client.egg-info/top_level.txt
test/test_account_creation_api.py
test/test_activate_post_dto.py
test/test_cancel_subscription_response.py
test/test_create_user_dto.py
test/test_create_user_response_dto.py
test/test_cyber_scan_exposures_get_dto.py
test/test_cyber_scan_exposures_get_dto_items_inner.py
