Metadata-Version: 1.2
Name: rd-idx-client
Version: 1.0.2
Summary: IDX API
Home-page: UNKNOWN
Author: OpenAPI Generator community
Author-email: support@idx.us
License: UNKNOWN
Keywords: OpenAPI,OpenAPI-Generator,IDX API
Platform: UNKNOWN
Requires-Python: >=3.6
